{
  "lastUpdated": "Imported CSV on 4/9/2026, 2:13:37 PM",
  "players": [
    {
      "name": "Bryson DeChambeau",
      "position": "T57",
      "toPar": "+3",
      "today": "+3",
      "thru": "17",
      "teeTime": "10:07 AM",
      "status": "Live",
      "madeCut": false,
      "isChampion": false,
      "scoreToPar": 3
    },
    {
      "name": "Jon Rahm",
      "position": "T57",
      "toPar": "+3",
      "today": "+3",
      "thru": "7",
      "teeTime": "1:08 PM",
      "status": "Live",
      "madeCut": false,
      "isChampion": false,
      "scoreToPar": 3
    },
    {
      "name": "Justin Rose",
      "position": "T9",
      "toPar": "-2",
      "today": "-2",
      "thru": "6",
      "teeTime": "1:20 PM",
      "status": "Live",
      "madeCut": false,
      "isChampion": false,
      "scoreToPar": -2
    },
    {
      "name": "Matt Fitzpatrick",
      "position": "T23",
      "toPar": "E",
      "today": "E",
      "thru": "17",
      "teeTime": "10:07 AM",
      "status": "Live",
      "madeCut": false,
      "isChampion": false,
      "scoreToPar": 0
    },
    {
      "name": "Robert MacIntyre",
      "position": "T23",
      "toPar": "E",
      "today": "E",
      "thru": "5",
      "teeTime": "1:44 PM",
      "status": "Live",
      "madeCut": false,
      "isChampion": false,
      "scoreToPar": 0
    },
    {
      "name": "JJ Spaun",
      "position": "T40",
      "toPar": "+1",
      "today": "+1",
      "thru": "8",
      "teeTime": "12:56 PM",
      "status": "Live",
      "madeCut": false,
      "isChampion": false,
      "scoreToPar": 1
    },
    {
      "name": "Shane Lowry",
      "position": "T9",
      "toPar": "-2",
      "today": "-2",
      "thru": "F",
      "teeTime": "9:43 AM",
      "status": "Live",
      "madeCut": false,
      "isChampion": false,
      "scoreToPar": -2
    },
    {
      "name": "Scottie Scheffler",
      "position": "T3",
      "toPar": "-3",
      "today": "-3",
      "thru": "5",
      "teeTime": "1:44 PM",
      "status": "Live",
      "madeCut": false,
      "isChampion": false,
      "scoreToPar": -3
    },
    {
      "name": "Cam Young",
      "position": "T40",
      "toPar": "+1",
      "today": "+1",
      "thru": "15",
      "teeTime": "10:31 AM",
      "status": "Live",
      "madeCut": false,
      "isChampion": false,
      "scoreToPar": 1
    },
    {
      "name": "Ludvig Aberg",
      "position": "T3",
      "toPar": "-3",
      "today": "-3",
      "thru": "7",
      "teeTime": "1:08 PM",
      "status": "Live",
      "madeCut": false,
      "isChampion": false,
      "scoreToPar": -3
    },
    {
      "name": "Jordan Spieth",
      "position": "T16",
      "toPar": "-1",
      "today": "-1",
      "thru": "6",
      "teeTime": "1:20 PM",
      "status": "Live",
      "madeCut": false,
      "isChampion": false,
      "scoreToPar": -1
    },
    {
      "name": "Brooks Koepka",
      "position": "T23",
      "toPar": "E",
      "today": "E",
      "thru": "6",
      "teeTime": "1:20 PM",
      "status": "Live",
      "madeCut": false,
      "isChampion": false,
      "scoreToPar": 0
    },
    {
      "name": "Justin Thomas",
      "position": "T9",
      "toPar": "-2",
      "today": "-2",
      "thru": "6",
      "teeTime": "1:32 PM",
      "status": "Live",
      "madeCut": false,
      "isChampion": false,
      "scoreToPar": -2
    },
    {
      "name": "Akshay Bhatia",
      "position": "T51",
      "toPar": "+2",
      "today": "+2",
      "thru": "17",
      "teeTime": "9:55 AM",
      "status": "Live",
      "madeCut": false,
      "isChampion": false,
      "scoreToPar": 2
    },
    {
      "name": "Rory McIlroy",
      "position": "T1",
      "toPar": "-5",
      "today": "-5",
      "thru": "15",
      "teeTime": "10:31 AM",
      "status": "Live",
      "madeCut": false,
      "isChampion": false,
      "scoreToPar": -5
    },
    {
      "name": "Xander Schauffele",
      "position": "T9",
      "toPar": "-2",
      "today": "-2",
      "thru": "17",
      "teeTime": "10:07 AM",
      "status": "Live",
      "madeCut": false,
      "isChampion": false,
      "scoreToPar": -2
    },
    {
      "name": "Tommy Fleetwood",
      "position": "T9",
      "toPar": "-2",
      "today": "-2",
      "thru": "17",
      "teeTime": "9:55 AM",
      "status": "Live",
      "madeCut": false,
      "isChampion": false,
      "scoreToPar": -2
    },
    {
      "name": "Patrick Cantlay",
      "position": "T66",
      "toPar": "+4",
      "today": "+4",
      "thru": "14",
      "teeTime": "10:43 AM",
      "status": "Live",
      "madeCut": false,
      "isChampion": false,
      "scoreToPar": 4
    },
    {
      "name": "Jake Knapp",
      "position": "T40",
      "toPar": "+1",
      "today": "+1",
      "thru": "F",
      "teeTime": "9:19 AM",
      "status": "Live",
      "madeCut": false,
      "isChampion": false,
      "scoreToPar": 1
    },
    {
      "name": "Hideki Matsuyama",
      "position": "T23",
      "toPar": "E",
      "today": "E",
      "thru": "16",
      "teeTime": "10:19 AM",
      "status": "Live",
      "madeCut": false,
      "isChampion": false,
      "scoreToPar": 0
    },
    {
      "name": "Chris Gotterup",
      "position": "T23",
      "toPar": "E",
      "today": "E",
      "thru": "7",
      "teeTime": "1:08 PM",
      "status": "Live",
      "madeCut": false,
      "isChampion": false,
      "scoreToPar": 0
    }
  ]
}
